{
    "lastPlayed": "file:///D:/My Documents/Y雅思口语/2024-5-8/P1素材/P1-work or studies.m4a",
    "position": 32549,
    "tracks": [
        {
            "url": "file:///D:/My Documents/Y雅思口语/2024-5-8/P1素材/P1-advertisements.m4a"
        },
        {
            "url": "file:///D:/My Documents/Y雅思口语/2024-5-8/P1素材/P1-cakes.m4a"
        },
        {
            "url": "file:///D:/My Documents/Y雅思口语/2024-5-8/P1素材/P1-celebrities.m4a"
        },
        {
            "url": "file:///D:/My Documents/Y雅思口语/2024-5-8/P1素材/P1-chatting.m4a"
        },
        {
            "url": "file:///D:/My Documents/Y雅思口语/2024-5-8/P1素材/P1-clothing.m4a"
        },
        {
            "url": "file:///D:/My Documents/Y雅思口语/2024-5-8/P1素材/P1-collecting things.m4a"
        },
        {
            "url": "file:///D:/My Documents/Y雅思口语/2024-5-8/P1素材/P1-colors.m4a"
        },
        {
            "url": "file:///D:/My Documents/Y雅思口语/2024-5-8/P1素材/P1-crowded places.m4a"
        },
        {
            "url": "file:///D:/My Documents/Y雅思口语/2024-5-8/P1素材/P1-feeling bored.m4a"
        },
        {
            "url": "file:///D:/My Documents/Y雅思口语/2024-5-8/P1素材/P1-films.m4a"
        },
        {
            "url": "file:///D:/My Documents/Y雅思口语/2024-5-8/P1素材/P1-fishing.m4a"
        },
        {
            "url": "file:///D:/My Documents/Y雅思口语/2024-5-8/P1素材/P1-geography.m4a"
        },
        {
            "url": "file:///D:/My Documents/Y雅思口语/2024-5-8/P1素材/P1-gifts.m4a"
        },
        {
            "url": "file:///D:/My Documents/Y雅思口语/2024-5-8/P1素材/P1-helping others.m4a"
        },
        {
            "url": "file:///D:/My Documents/Y雅思口语/2024-5-8/P1素材/P1-home.m4a"
        },
        {
            "url": "file:///D:/My Documents/Y雅思口语/2024-5-8/P1素材/P1-hometown.m4a"
        },
        {
            "url": "file:///D:/My Documents/Y雅思口语/2024-5-8/P1素材/P1-losing things.m4a"
        },
        {
            "url": "file:///D:/My Documents/Y雅思口语/2024-5-8/P1素材/P1-maps.m4a"
        },
        {
            "url": "file:///D:/My Documents/Y雅思口语/2024-5-8/P1素材/P1-memory.m4a"
        },
        {
            "url": "file:///D:/My Documents/Y雅思口语/2024-5-8/P1素材/P1-money.m4a"
        },
        {
            "url": "file:///D:/My Documents/Y雅思口语/2024-5-8/P1素材/P1-musical instruments.m4a"
        },
        {
            "url": "file:///D:/My Documents/Y雅思口语/2024-5-8/P1素材/P1-noise.m4a"
        },
        {
            "url": "file:///D:/My Documents/Y雅思口语/2024-5-8/P1素材/P1-robots.m4a"
        },
        {
            "url": "file:///D:/My Documents/Y雅思口语/2024-5-8/P1素材/P1-running.m4a"
        },
        {
            "url": "file:///D:/My Documents/Y雅思口语/2024-5-8/P1素材/P1-singing.m4a"
        },
        {
            "url": "file:///D:/My Documents/Y雅思口语/2024-5-8/P1素材/P1-staying at home.m4a"
        },
        {
            "url": "file:///D:/My Documents/Y雅思口语/2024-5-8/P1素材/P1-sunglasses.m4a"
        },
        {
            "url": "file:///D:/My Documents/Y雅思口语/2024-5-8/P1素材/P1-tea and coffee.m4a"
        },
        {
            "url": "file:///D:/My Documents/Y雅思口语/2024-5-8/P1素材/P1-the area you live in.m4a"
        },
        {
            "url": "file:///D:/My Documents/Y雅思口语/2024-5-8/P1素材/P1-transport.m4a"
        },
        {
            "url": "file:///D:/My Documents/Y雅思口语/2024-5-8/P1素材/P1-travel.m4a"
        },
        {
            "url": "file:///D:/My Documents/Y雅思口语/2024-5-8/P1素材/P1-video games.m4a"
        },
        {
            "url": "file:///D:/My Documents/Y雅思口语/2024-5-8/P1素材/P1-work or studies.m4a"
        },
        {
            "url": "file:///D:/My Documents/Y雅思口语/2024-5-8/P2素材/P2-a difficult task that you completed at work or study that you felt proud of.m4a"
        },
        {
            "url": "file:///D:/My Documents/Y雅思口语/2024-5-8/P2素材/P2-a drawing or painting you like.m4a"
        },
        {
            "url": "file:///D:/My Documents/Y雅思口语/2024-5-8/P2素材/P2-a film that you felt strongly about.m4a"
        },
        {
            "url": "file:///D:/My Documents/Y雅思口语/2024-5-8/P2素材/P2-a foreigner who speaks your language well.m4a"
        },
        {
            "url": "file:///D:/My Documents/Y雅思口语/2024-5-8/P2素材/P2-a good advertisement that you think is useful.m4a"
        },
        {
            "url": "file:///D:/My Documents/Y雅思口语/2024-5-8/P2素材/P2-a great team member you have worked with.m4a"
        },
        {
            "url": "file:///D:/My Documents/Y雅思口语/2024-5-8/P2素材/P2-a job that you would not like to do in the future.m4a"
        },
        {
            "url": "file:///D:/My Documents/Y雅思口语/2024-5-8/P2素材/P2-a long-term goal you would like to achieve.m4a"
        },
        {
            "url": "file:///D:/My Documents/Y雅思口语/2024-5-8/P2素材/P2-a park or a garden in your city.m4a"
        },
        {
            "url": "file:///D:/My Documents/Y雅思口语/2024-5-8/P2素材/P2-a party that you enjoyed.m4a"
        },
        {
            "url": "file:///D:/My Documents/Y雅思口语/2024-5-8/P2素材/P2-a period of time that changed your life.m4a"
        },
        {
            "url": "file:///D:/My Documents/Y雅思口语/2024-5-8/P2素材/P2-a person who always has interesting ideas or opinions.m4a"
        },
        {
            "url": "file:///D:/My Documents/Y雅思口语/2024-5-8/P2素材/P2-a person who likes to cook for others.m4a"
        },
        {
            "url": "file:///D:/My Documents/Y雅思口语/2024-5-8/P2素材/P2-a person who you think is good at welcoming visitors.m4a"
        },
        {
            "url": "file:///D:/My Documents/Y雅思口语/2024-5-8/P2素材/P2-a person you know who likes to talk a lot.m4a"
        },
        {
            "url": "file:///D:/My Documents/Y雅思口语/2024-5-8/P2素材/P2-a photo that makes you feel happy.m4a"
        },
        {
            "url": "file:///D:/My Documents/Y雅思口语/2024-5-8/P2素材/P2-a place in your country that you think is interesting.m4a"
        },
        {
            "url": "file:///D:/My Documents/Y雅思口语/2024-5-8/P2素材/P2-a place you would like to go to relax.m4a"
        },
        {
            "url": "file:///D:/My Documents/Y雅思口语/2024-5-8/P2素材/P2-a public facility that has been renovated and improved.m4a"
        },
        {
            "url": "file:///D:/My Documents/Y雅思口语/2024-5-8/P2素材/P2-a rule that is important in your school or at work.m4a"
        },
        {
            "url": "file:///D:/My Documents/Y雅思口语/2024-5-8/P2素材/P2-a science subject that you are interested in.m4a"
        },
        {
            "url": "file:///D:/My Documents/Y雅思口语/2024-5-8/P2素材/P2-a skill that you learned as a teenager.m4a"
        },
        {
            "url": "file:///D:/My Documents/Y雅思口语/2024-5-8/P2素材/P2-a sportsperson you admire.m4a"
        },
        {
            "url": "file:///D:/My Documents/Y雅思口语/2024-5-8/P2素材/P2-a successful businessperson you know.m4a"
        },
        {
            "url": "file:///D:/My Documents/Y雅思口语/2024-5-8/P2素材/P2-a time when there was a lot of noise.m4a"
        },
        {
            "url": "file:///D:/My Documents/Y雅思口语/2024-5-8/P2素材/P2-a time when you bought something from a street market.m4a"
        },
        {
            "url": "file:///D:/My Documents/Y雅思口语/2024-5-8/P2素材/P2-a time when you had a problem using a computer.m4a"
        },
        {
            "url": "file:///D:/My Documents/Y雅思口语/2024-5-8/P2素材/P2-a time when you received bad service in a restaurant  or shop.m4a"
        },
        {
            "url": "file:///D:/My Documents/Y雅思口语/2024-5-8/P2素材/P2-a time when you taught a friend or relative something.m4a"
        },
        {
            "url": "file:///D:/My Documents/Y雅思口语/2024-5-8/P2素材/P2-a trip that you were looking forward to but was delayed.m4a"
        },
        {
            "url": "file:///D:/My Documents/Y雅思口语/2024-5-8/P2素材/P2-a uniform you wear.m4a"
        },
        {
            "url": "file:///D:/My Documents/Y雅思口语/2024-5-8/P2素材/P2-a useful object in your home that you cannot live without.m4a"
        },
        {
            "url": "file:///D:/My Documents/Y雅思口语/2024-5-8/P2素材/P2-an activity that made you feel tired.m4a"
        },
        {
            "url": "file:///D:/My Documents/Y雅思口语/2024-5-8/P2素材/P2-an item you lost and then found.m4a"
        },
        {
            "url": "file:///D:/My Documents/Y雅思口语/2024-5-8/P2素材/P2-an occasion when you had to do something in a hurry.m4a"
        },
        {
            "url": "file:///D:/My Documents/Y雅思口语/2024-5-8/P2素材/P2-an occasion when you heard someone complaining about something.m4a"
        },
        {
            "url": "file:///D:/My Documents/Y雅思口语/2024-5-8/P2素材/P2-an occasion when you used a map.m4a"
        },
        {
            "url": "file:///D:/My Documents/Y雅思口语/2024-5-8/P2素材/P2-an occasion when you waited a long time for something nice to happen.m4a"
        },
        {
            "url": "file:///D:/My Documents/Y雅思口语/2024-5-8/P2素材/P2-an outdoor activity you did.m4a"
        },
        {
            "url": "file:///D:/My Documents/Y雅思口语/2024-5-8/P2素材/P2-an unusual holiday you had.m4a"
        },
        {
            "url": "file:///D:/My Documents/Y雅思口语/2024-5-8/P2素材/P2-something in your country that you are interested in.m4a"
        },
        {
            "url": "file:///D:/My Documents/Y雅思口语/2024-5-8/P2素材/P2-something you do regularly to help yourself work or study.m4a"
        }
    ]
}
